herocare_api_python_sdk/__init__.py
herocare_api_python_sdk-0.0.0.dist-info/METADATA
herocare_api_python_sdk-0.0.0.dist-info/WHEEL
herocare_api_python_sdk-0.0.0.dist-info/top_level.txt
herocare_api_python_sdk-0.0.0.dist-info/RECORD
