Metadata-Version: 2.2
Name: herocare-api-python-sdk
Version: 0.0.0
Summary: A name reservation package
Author-email: fix deps <fix@python.deps>
Classifier: Programming Language :: Python :: 3
Classifier: License :: OSI Approved :: MIT License
Classifier: Operating System :: OS Independent
Requires-Python: >=3.0
